[{"__type__":"cc.SpriteFrame","content":{"name":"小金币","texture":"12d6087ff","rect":[253,1851,38,40],"offset":[0,0],"originalSize":[38,40],"capInsets":[0,0,0,0]}},[{"__type__":"cc.Prefab","_name":"coin","data":{"__id__":1}},{"__type__":"cc.Node","_name":"coin","_components":[{"__type__":"cc.Sprite","node":{"__id__":1},"_materials":[{"__uuid__":"ecpdLyjvZBwrvm+cedCcQy"}],"_spriteFrame":{"__uuid__":"77NiXEN1hKfKHkTOwQ2oyN"}},{"__type__":"406dco9odlP26BLd5jEtp7i","node":{"__id__":1}}],"_prefab":{"__type__":"cc.PrefabInfo","root":{"__id__":1},"asset":{"__uuid__":"e1AI/+JwRHRI/yfL2dkjZw"},"fileId":"708Kxa6+NDOaS2XmFNz1jl"},"_contentSize":{"__type__":"cc.Size","width":38,"height":40},"_trs":{"__type__":"TypedArray","ctor":"Float64Array","array":[0,0,0,0,0,0,1,1,1,1]}}]]