[[{"__type__":"cc.Prefab","_name":"totalFormVIVO","data":{"__id__":1}},{"__type__":"cc.Node","_name":"totalFormVIVO","_children":[{"__id__":2},{"__id__":17}],"_components":[{"__type__":"cc.Sprite","node":{"__id__":1},"_materials":[{"__uuid__":"ecpdLyjvZBwrvm+cedCcQy"}],"_sizeMode":0},{"__type__":"cc.Widget","node":{"__id__":1},"_alignFlags":45,"_originalWidth":40,"_originalHeight":36},{"__type__":"3ba12QmsfNNZKwG6vcsKXdS","node":{"__id__":1},"checked":{"__id__":6},"unchecked":{"__id__":9},"btnReceive":{"__id__":3},"levelCoin":{"__id__":11},"txtMemo":{"__id__":8},"btnShortcut":{"__id__":17}}],"_prefab":{"__type__":"cc.PrefabInfo","root":{"__id__":1},"asset":{"__uuid__":"94C1GAAfRNeqg6WVlQPnlH"},"fileId":"67jxGizfxJa43VvnbdfLKU"},"_contentSize":{"__type__":"cc.Size","width":1334,"height":750},"_trs":{"__type__":"TypedArray","ctor":"Float64Array","array":[667,375,0,0,0,0,1,1,1,1]},"_groupIndex":8,"groupIndex":8},{"__type__":"cc.Node","_name":"winContainer","_parent":{"__id__":1},"_children":[{"__id__":3},{"__id__":4},{"__id__":10},{"__id__":12},{"__id__":13},{"__id__":14}],"_prefab":{"__type__":"cc.PrefabInfo","root":{"__id__":1},"asset":{"__uuid__":"94C1GAAfRNeqg6WVlQPnlH"},"fileId":"c53fWuODxDcbdrg6uclDAE"},"_trs":{"__type__":"TypedArray","ctor":"Float64Array","array":[0,0,0,0,0,0,1,1,1,1]}},{"__type__":"cc.Node","_name":"btnWinReceive","_parent":{"__id__":2},"_components":[{"__type__":"cc.Sprite","node":{"__id__":3},"_materials":[{"__uuid__":"ecpdLyjvZBwrvm+cedCcQy"}],"_spriteFrame":{"__uuid__":"50p9+XfJhPEK7feNpiy4hP"},"_sizeMode":0},{"__type__":"9c1e2AO8wZPWbAgk+CIA9Na","node":{"__id__":3}}],"_prefab":{"__type__":"cc.PrefabInfo","root":{"__id__":1},"asset":{"__uuid__":"94C1GAAfRNeqg6WVlQPnlH"},"fileId":"b91QbCLFdOFbAxqjIOXobx"},"_opacity":200,"_contentSize":{"__type__":"cc.Size","width":145,"height":38},"_trs":{"__type__":"TypedArray","ctor":"Float64Array","array":[1.634,-133.177,0,0,0,0,1,1,1,1]},"_groupIndex":8,"groupIndex":8},{"__type__":"cc.Node","_name":"unchecked","_parent":{"__id__":2},"_children":[{"__id__":5},{"__id__":7}],"_active":false,"_components":[{"__id__":9}],"_prefab":{"__type__":"cc.PrefabInfo","root":{"__id__":1},"asset":{"__uuid__":"94C1GAAfRNeqg6WVlQPnlH"},"fileId":"62FwIQsjVLiItBGIP/COzp"},"_contentSize":{"__type__":"cc.Size","width":43,"height":43},"_trs":{"__type__":"TypedArray","ctor":"Float64Array","array":[-106.283,40.772,0,0,0,0,1,1,1,1]}},{"__type__":"cc.Node","_name":"checked","_parent":{"__id__":4},"_components":[{"__id__":6}],"_prefab":{"__type__":"cc.PrefabInfo","root":{"__id__":1},"asset":{"__uuid__":"94C1GAAfRNeqg6WVlQPnlH"},"fileId":"22ZPqPqC1MW4oN58+PcUPi"},"_contentSize":{"__type__":"cc.Size","width":43,"height":43},"_trs":{"__type__":"TypedArray","ctor":"Float64Array","array":[0,0,0,0,0,0,1,1,1,1]}},{"__type__":"cc.Sprite","node":{"__id__":5},"_materials":[{"__uuid__":"ecpdLyjvZBwrvm+cedCcQy"}],"_spriteFrame":{"__uuid__":"73qq+ZtZlMVKLyRt9xVDp1"}},{"__type__":"cc.Node","_name":"txtMemo","_parent":{"__id__":4},"_components":[{"__id__":8}],"_prefab":{"__type__":"cc.PrefabInfo","root":{"__id__":1},"asset":{"__uuid__":"94C1GAAfRNeqg6WVlQPnlH"},"fileId":"66Jox3TM5NiKi5wer3SzBU"},"_contentSize":{"__type__":"cc.Size","width":182.25,"height":50.4},"_trs":{"__type__":"TypedArray","ctor":"Float64Array","array":[117.547,0,0,0,0,0,1,1,1,1]}},{"__type__":"cc.Label","node":{"__id__":7},"_materials":[{"__uuid__":"ecpdLyjvZBwrvm+cedCcQy"}],"_useOriginalSize":false,"_string":"看视频5倍","_N$string":"看视频5倍","_N$horizontalAlign":1,"_N$verticalAlign":1},{"__type__":"cc.Sprite","node":{"__id__":4},"_materials":[{"__uuid__":"ecpdLyjvZBwrvm+cedCcQy"}],"_spriteFrame":{"__uuid__":"1dLOrd2NhMv4/bInr6QVIg"}},{"__type__":"cc.Node","_name":"coinNum","_parent":{"__id__":2},"_components":[{"__id__":11}],"_prefab":{"__type__":"cc.PrefabInfo","root":{"__id__":1},"asset":{"__uuid__":"94C1GAAfRNeqg6WVlQPnlH"},"fileId":"1azVBdq3tCfqaRU/P2BrDA"},"_contentSize":{"__type__":"cc.Size","width":120,"height":50},"_trs":{"__type__":"TypedArray","ctor":"Float64Array","array":[5.919,101.03,0,0,0,0,1,1,1,1]}},{"__type__":"cc.Label","node":{"__id__":10},"_materials":[{"__uuid__":"ecpdLyjvZBwrvm+cedCcQy"}],"_useOriginalSize":false,"_string":"00.00","_N$string":"00.00","_fontSize":32,"_lineHeight":32,"_N$horizontalAlign":1,"_N$verticalAlign":1,"_N$overflow":2},{"__type__":"cc.Node","_name":"大金币","_parent":{"__id__":2},"_components":[{"__type__":"cc.Sprite","node":{"__id__":12},"_materials":[{"__uuid__":"ecpdLyjvZBwrvm+cedCcQy"}],"_spriteFrame":{"__uuid__":"feGLaSUu1BRbixbwyLPcqI"}}],"_prefab":{"__type__":"cc.PrefabInfo","root":{"__id__":1},"asset":{"__uuid__":"94C1GAAfRNeqg6WVlQPnlH"},"fileId":"a1SC6voedBfL81ZWtnvSTi"},"_contentSize":{"__type__":"cc.Size","width":46,"height":51},"_trs":{"__type__":"TypedArray","ctor":"Float64Array","array":[-74.51,102.017,0,0,0,0,1,1,1,1]}},{"__type__":"cc.Node","_name":"恭喜获得","_parent":{"__id__":2},"_components":[{"__type__":"cc.Sprite","node":{"__id__":13},"_materials":[{"__uuid__":"ecpdLyjvZBwrvm+cedCcQy"}],"_spriteFrame":{"__uuid__":"08+NttIh5J8r10RcSKi5av"}}],"_prefab":{"__type__":"cc.PrefabInfo","root":{"__id__":1},"asset":{"__uuid__":"94C1GAAfRNeqg6WVlQPnlH"},"fileId":"43kS4xK3VGuqazTumBSAAb"},"_contentSize":{"__type__":"cc.Size","width":316,"height":187},"_trs":{"__type__":"TypedArray","ctor":"Float64Array","array":[-2.778,184.855,0,0,0,0,1,1,1,1]}},{"__type__":"cc.Node","_name":"btnVideo","_parent":{"__id__":2},"_children":[{"__id__":15},{"__id__":16}],"_components":[{"__type__":"cc.Sprite","node":{"__id__":14},"_materials":[{"__uuid__":"ecpdLyjvZBwrvm+cedCcQy"}],"_spriteFrame":{"__uuid__":"d7HZn+IvxN5I4X1fiw4xou"}},{"__type__":"9c1e2AO8wZPWbAgk+CIA9Na","node":{"__id__":14},"autoScale":true,"zoomTime":0.5}],"_prefab":{"__type__":"cc.PrefabInfo","root":{"__id__":1},"asset":{"__uuid__":"94C1GAAfRNeqg6WVlQPnlH"},"fileId":"98sk5sIp9MQLqI7R3WFQNn"},"_contentSize":{"__type__":"cc.Size","width":254,"height":90},"_trs":{"__type__":"TypedArray","ctor":"Float64Array","array":[0,-7.534,0,0,0,0,1,1,1,1]}},{"__type__":"cc.Node","_name":"立即领取","_parent":{"__id__":14},"_components":[{"__type__":"cc.Sprite","node":{"__id__":15},"_materials":[{"__uuid__":"ecpdLyjvZBwrvm+cedCcQy"}],"_spriteFrame":{"__uuid__":"3dkc7URQVOeI+4c/Vp7wcX"}}],"_prefab":{"__type__":"cc.PrefabInfo","root":{"__id__":1},"asset":{"__uuid__":"94C1GAAfRNeqg6WVlQPnlH"},"fileId":"f2wT6cHiVNc4JqyPdtkGiI"},"_contentSize":{"__type__":"cc.Size","width":147,"height":40},"_trs":{"__type__":"TypedArray","ctor":"Float64Array","array":[19.829,4,0,0,0,0,1,1,1,1]}},{"__type__":"cc.Node","_name":"视频图标","_parent":{"__id__":14},"_components":[{"__type__":"cc.Sprite","node":{"__id__":16},"_materials":[{"__uuid__":"ecpdLyjvZBwrvm+cedCcQy"}],"_spriteFrame":{"__uuid__":"acJRz7ZGZLtYchepD0Ds4U"}}],"_prefab":{"__type__":"cc.PrefabInfo","root":{"__id__":1},"asset":{"__uuid__":"94C1GAAfRNeqg6WVlQPnlH"},"fileId":"0bKs5v+BhH0IN5yj/ADCi2"},"_contentSize":{"__type__":"cc.Size","width":34,"height":27},"_trs":{"__type__":"TypedArray","ctor":"Float64Array","array":[-73.259,1.246,0,0,0,0,1,1,1,1]}},{"__type__":"cc.Node","_name":"New Node","_parent":{"__id__":1},"_children":[{"__id__":18},{"__id__":19}],"_active":false,"_components":[{"__type__":"9c1e2AO8wZPWbAgk+CIA9Na","node":{"__id__":17}}],"_prefab":{"__type__":"cc.PrefabInfo","root":{"__id__":1},"asset":{"__uuid__":"94C1GAAfRNeqg6WVlQPnlH"},"fileId":"056wrWJZ9MgaX6KyN21LiZ"},"_contentSize":{"__type__":"cc.Size","width":200,"height":50},"_trs":{"__type__":"TypedArray","ctor":"Float64Array","array":[564.879,0,0,0,0,0,1,1,1,1]}},{"__type__":"cc.Node","_name":"btn-green","_parent":{"__id__":17},"_components":[{"__type__":"cc.Sprite","node":{"__id__":18},"_materials":[{"__uuid__":"ecpdLyjvZBwrvm+cedCcQy"}],"_spriteFrame":{"__uuid__":"c28IUJ9jFLUK6qTU4zPI1e"}}],"_prefab":{"__type__":"cc.PrefabInfo","root":{"__id__":1},"asset":{"__uuid__":"94C1GAAfRNeqg6WVlQPnlH"},"fileId":"000WBNI7JHsrdk64CPOrIh"},"_contentSize":{"__type__":"cc.Size","width":202,"height":75},"_trs":{"__type__":"TypedArray","ctor":"Float64Array","array":[0,0,0,0,0,0,1,0.8,0.8,1]}},{"__type__":"cc.Node","_name":"New Label","_parent":{"__id__":17},"_components":[{"__type__":"cc.Label","node":{"__id__":19},"_materials":[{"__uuid__":"ecpdLyjvZBwrvm+cedCcQy"}],"_useOriginalSize":false,"_string":"添加到桌面","_N$string":"添加到桌面","_fontSize":32,"_lineHeight":32,"_enableWrapText":false,"_N$horizontalAlign":1,"_N$verticalAlign":1,"_N$overflow":2}],"_prefab":{"__type__":"cc.PrefabInfo","root":{"__id__":1},"asset":{"__uuid__":"94C1GAAfRNeqg6WVlQPnlH"},"fileId":"3f2AP8fuxLVoJpiUhaCyAh"},"_color":{"__type__":"cc.Color","r":49,"g":49,"b":3},"_contentSize":{"__type__":"cc.Size","width":150,"height":50.4},"_trs":{"__type__":"TypedArray","ctor":"Float64Array","array":[0,3,0,0,0,0,1,1,1,1]}}],{"__type__":"cc.SpriteFrame","content":{"name":"蓝按钮","texture":"fbNMbHcRZIYI28gxIB3jDr","rect":[0,0,202,75],"offset":[0,0],"originalSize":[202,75],"capInsets":[0,0,0,0]}}]